imgoptimize/__init__.py
imgoptimize/image_optimizer.py
tinify/__init__.py
tinify/client.py
tinify/errors.py
tinify/result.py
tinify/result_meta.py
tinify/source.py
tinify/version.py
tinify/data/cacert.pem
imgoptimizer-0.0.4.dist-info/LICENSE
imgoptimizer-0.0.4.dist-info/METADATA
imgoptimizer-0.0.4.dist-info/WHEEL
imgoptimizer-0.0.4.dist-info/top_level.txt
imgoptimizer-0.0.4.dist-info/RECORD
