Metadata-Version: 2.1
Name: imgoptimizer
Version: 0.0.4
Summary: e. Optimize image size, make thumbnail, cover, and upload directly to S3
Home-page: https://github.com/ucodevn/image_optimizer
Author: Thuc Nguyen, Quy PhamNgoc
Author-email: gthuc.nguyen@gmail.com
License: MIT
Download-URL: https://github.com/ucodevn/image_optimizer
Keywords: Image,Optimize,S3
Platform: UNKNOWN
Requires-Dist: Pillow
Requires-Dist: requests
Requires-Dist: boto3
